sokconfig/__init__.py
sokconfig/settings.py
sokconfig/values.py
sokconfig-1.0.0.dist-info/METADATA
sokconfig-1.0.0.dist-info/WHEEL
sokconfig-1.0.0.dist-info/RECORD
