Metadata-Version: 2.1
Name: sokconfig
Version: 1.0.0
Summary: A simple config parser for python
Home-page: https://github.com/sokripon/sokconfig
Author: sokripon
Author-email: sokripon@gmail.com
Requires-Python: >=3.10,<4.0
Classifier: Programming Language :: Python :: 3
Classifier: Programming Language :: Python :: 3.10
Classifier: Programming Language :: Python :: 3.11
Classifier: Programming Language :: Python :: 3.12
Project-URL: Repository, https://github.com/sokripon/sokconfig
